<Map Name="Duel">
	<Planets>
		<Planet Id="1" Name="Alpha"       BaseUnitsPerTurn="5" X="-300" Y="-200" Z="0" Radius="35" Diffuse="Textures\\MarsDiffuse" />
		<Planet Id="2" Name="Beta"        BaseUnitsPerTurn="3" X="-300" Y="100"  Z="0" Radius="45" Diffuse="Textures\\VenusDiffuse" />
		<Planet Id="3" Name="Gamma"       BaseUnitsPerTurn="3" X="0"    Y="-200" Z="0" Radius="55" Diffuse="Textures\\JupiterDiffuse" />
		<Planet Id="4" Name="A"           BaseUnitsPerTurn="5" X="200"  Y="300"  Z="0" Radius="25" Diffuse="Textures\\MoonDiffuse" />
		<Planet Id="5" Name="B" 		      BaseUnitsPerTurn="3" X="0"    Y="300"  Z="0" Radius="40" Diffuse="Textures\\EarthDiffuse" Clouds="Textures\\EarthClouds" CloudsAlpha="Textures\\EarthCloudsAlpha" />
		<Planet Id="6" Name="C" 		      BaseUnitsPerTurn="3" X="200"  Y="100"  Z="0" Radius="30" Diffuse="Textures\\PlutonDiffuse" />
		<Planet Id="7" Name="Core Prime"  BaseUnitsPerTurn="6" X="0"    Y="100"  Z="0" Radius="50" Diffuse="Textures\\PlanetDiffuse1" />
	</Planets>
	
	<Links>
		<PlanetLink SourceId="1" TargetId="2"/>
		<PlanetLink SourceId="1" TargetId="3"/>
		<PlanetLink SourceId="2" TargetId="7"/>
		<PlanetLink SourceId="3" TargetId="7"/>
		<PlanetLink SourceId="7" TargetId="5"/>
		<PlanetLink SourceId="7" TargetId="6"/>
		<PlanetLink SourceId="4" TargetId="5"/>
		<PlanetLink SourceId="4" TargetId="6"/>
	</Links>
	
	<Systems>
		<PlanetarySystem Name="Southern Sector" FleetBonusPerTurn="4" Id="1">
			<Planets>
				<PlanetId>1</PlanetId>
				<PlanetId>2</PlanetId>
				<PlanetId>3</PlanetId>			
			</Planets>
		</PlanetarySystem>
		<PlanetarySystem Name="Northern Sector" FleetBonusPerTurn="4" Id="2">
			<Planets>
				<PlanetId>4</PlanetId>
				<PlanetId>5</PlanetId>
				<PlanetId>6</PlanetId>
			</Planets>
		</PlanetarySystem>		
	</Systems>
	
	<PlayerStartingData>
		<StartingData PlanetId="1"/>
		<StartingData PlanetId="4"/>
	</PlayerStartingData>
</Map>
